odoo9_addon_stock_warehouse_orderpoint_stock_info_unreserved-9.0.1.0.0-py2.7-nspkg.pth
odoo9_addon_stock_warehouse_orderpoint_stock_info_unreserved-9.0.1.0.0.dist-info/DESCRIPTION.rst
odoo9_addon_stock_warehouse_orderpoint_stock_info_unreserved-9.0.1.0.0.dist-info/METADATA
odoo9_addon_stock_warehouse_orderpoint_stock_info_unreserved-9.0.1.0.0.dist-info/RECORD
odoo9_addon_stock_warehouse_orderpoint_stock_info_unreserved-9.0.1.0.0.dist-info/WHEEL
odoo9_addon_stock_warehouse_orderpoint_stock_info_unreserved-9.0.1.0.0.dist-info/metadata.json
odoo9_addon_stock_warehouse_orderpoint_stock_info_unreserved-9.0.1.0.0.dist-info/namespace_packages.txt
odoo9_addon_stock_warehouse_orderpoint_stock_info_unreserved-9.0.1.0.0.dist-info/top_level.txt
odoo_addons/stock_warehouse_orderpoint_stock_info_unreserved/README.rst
odoo_addons/stock_warehouse_orderpoint_stock_info_unreserved/__init__.py
odoo_addons/stock_warehouse_orderpoint_stock_info_unreserved/__openerp__.py
odoo_addons/stock_warehouse_orderpoint_stock_info_unreserved/models/__init__.py
odoo_addons/stock_warehouse_orderpoint_stock_info_unreserved/models/stock_warehouse_orderpoint.py
odoo_addons/stock_warehouse_orderpoint_stock_info_unreserved/tests/__init__.py
odoo_addons/stock_warehouse_orderpoint_stock_info_unreserved/tests/test_stock_warehouse_orderpoint.py
odoo_addons/stock_warehouse_orderpoint_stock_info_unreserved/views/stock_warehouse_orderpoint_view.xml
